LICENSE
README.md
setup.py
metasequoia_sql/__init__.py
metasequoia_sql/config.py
metasequoia_sql/errors.py
metasequoia_sql.egg-info/PKG-INFO
metasequoia_sql.egg-info/SOURCES.txt
metasequoia_sql.egg-info/dependency_links.txt
metasequoia_sql.egg-info/top_level.txt
metasequoia_sql/analyzer/__init__.py
metasequoia_sql/analyzer/base.py
metasequoia_sql/analyzer/node.py
metasequoia_sql/analyzer/tool.py
metasequoia_sql/analyzer/data_linage/__init__.py
metasequoia_sql/analyzer/data_linage/table_lineage.py
metasequoia_sql/analyzer/data_linage/table_lineage_analyzer.py
metasequoia_sql/analyzer/data_linage/table_lineage_storage.py
metasequoia_sql/analyzer/toolkit/__init__.py
metasequoia_sql/analyzer/toolkit/all_level_standard_table.py
metasequoia_sql/analyzer/toolkit/current_level_column_analyzer.py
metasequoia_sql/analyzer/toolkit/current_level_sub_query.py
metasequoia_sql/analyzer/toolkit/current_level_table_name_analyzer.py
metasequoia_sql/analyzer/toolkit/current_level_used_quote_columns.py
metasequoia_sql/common/__init__.py
metasequoia_sql/common/basic.py
metasequoia_sql/common/char_set.py
metasequoia_sql/common/name_set.py
metasequoia_sql/common/scanner.py
metasequoia_sql/common/static.py
metasequoia_sql/core/__init__.py
metasequoia_sql/core/node.py
metasequoia_sql/core/parser.py
metasequoia_sql/core/sql_type.py
metasequoia_sql/core/static.py
metasequoia_sql/lexical/__init__.py
metasequoia_sql/lexical/amt_node.py
metasequoia_sql/lexical/fsm_machine.py
metasequoia_sql/lexical/fsm_memory.py
metasequoia_sql/lexical/fsm_operate.py
metasequoia_sql/lexical/fsm_operation_map.py
metasequoia_sql/lexical/fsm_status.py
metasequoia_sql/plugins/__init__.py
metasequoia_sql/plugins/mybaitis.py