Metadata-Version: 2.1
Name: metasequoia-sql
Version: 0.6.0
Summary: metasequoia-sql 是一款注重性能的 SQL 语法的解析和分析器，适用于 SQL 的格式化、执行和分析场景，致力于打造性能最高的 Python 版 SQL 解析器。
Home-page: https://github.com/ChangxingJiang/metasequoia-sql
Author: changxing
Author-email: 1278729001@qq.com
License: MIT License
Platform: all
Classifier: Intended Audience :: Developers
Classifier: Operating System :: OS Independent
Classifier: Natural Language :: Chinese (Simplified)
Classifier: Programming Language :: Python
Classifier: Programming Language :: Python :: 3.10
Classifier: Programming Language :: Python :: 3.11
Classifier: Programming Language :: Python :: 3.12
Classifier: Topic :: Software Development :: Libraries
License-File: LICENSE
